pydpp/__init__.py
pydpp/dpp.py
pydpp/kernels.py
pydpp/utils.py
pydpp-0.2.1.dist-info/METADATA
pydpp-0.2.1.dist-info/RECORD
pydpp-0.2.1.dist-info/WHEEL
pydpp-0.2.1.dist-info/top_level.txt
