Metadata-Version: 2.1
Name: pydpp
Version: 0.2.1
Summary: A python package for sampling from determinantal point processes
Home-page: https://github.com/satwik77/pyDPP
Author: Satwik Bhattamishra
Author-email: satwik55@gmail.com
License: MIT
Platform: UNKNOWN
Classifier: Development Status :: 2 - Pre-Alpha
Classifier: License :: OSI Approved :: MIT License
Classifier: Programming Language :: Python
Classifier: Programming Language :: Python :: 2
Classifier: Programming Language :: Python :: 2.7
Classifier: Programming Language :: Python :: 3
Classifier: Programming Language :: Python :: 3.4
Classifier: Programming Language :: Python :: 3.5
Classifier: Programming Language :: Python :: 3.6
Classifier: Programming Language :: Python :: 3.7
Requires-Dist: numpy (>=1.1.0)
Requires-Dist: scipy (>=1.1.0)
